llm_project_summarizer/__init__.py
llm_project_summarizer/cli.py
llm_project_summarizer/parsers/base.py
llm_project_summarizer/parsers/go.py
llm_project_summarizer/parsers/python.py
llm_project_summarizer/summarizer.py
llm_project_summarizer-0.0.4.dist-info/LICENSE
llm_project_summarizer-0.0.4.dist-info/METADATA
llm_project_summarizer-0.0.4.dist-info/WHEEL
llm_project_summarizer-0.0.4.dist-info/entry_points.txt
llm_project_summarizer-0.0.4.dist-info/RECORD
